nought/__init__.py
nought/__main__.py
nought/conf.toml
nought/easteregg.py
nought/runner.py
nought/wizard.py
nought-1.0.8.data/scripts/nought
nought-1.0.8.data/scripts/nt
nought-1.0.8.dist-info/LICENSE
nought-1.0.8.dist-info/METADATA
nought-1.0.8.dist-info/WHEEL
nought-1.0.8.dist-info/entry_points.txt
nought-1.0.8.dist-info/top_level.txt
nought-1.0.8.dist-info/RECORD
