Metadata-Version: 2.1
Name: nought
Version: 1.0.8
Summary: A super customizable file cleaner/organizer/automator
Home-page: https://github.com/cole-wilson/nought
Author: Cole Wilson
Author-email: cole@colewilson.xyz
License: Apache-2.0
Project-URL: Documentation, https://github.com/cole-wilson/nought
Project-URL: Questions, https://github.com/cole-wilson/nought
Project-URL: Source, https://github.com/cole-wilson/nought
Project-URL: Tracker, https://github.com/cole-wilson/nought/issues
Keywords: nought file organizer desktop cleaner declutterer devtools tools tool
Platform: UNKNOWN
Classifier: Programming Language :: Python :: 3
Requires-Python: >=3.6
Requires-Dist: toml
Requires-Dist: requests
